gianna/__init__.py
gianna/assistants/__init__.py
gianna/assistants/audio/__init__.py
gianna/assistants/audio/players/__init__.py
gianna/assistants/audio/players/aac.py
gianna/assistants/audio/players/abstract_players.py
gianna/assistants/audio/players/factories.py
gianna/assistants/audio/players/factory_method.py
gianna/assistants/audio/players/flac.py
gianna/assistants/audio/players/m4a.py
gianna/assistants/audio/players/mp3.py
gianna/assistants/audio/players/ogg.py
gianna/assistants/audio/players/wave.py
gianna/assistants/audio/recorders/__init__.py
gianna/assistants/audio/recorders/abstract_recorders.py
gianna/assistants/audio/recorders/basics.py
gianna/assistants/audio/recorders/factories.py
gianna/assistants/audio/recorders/factory_method.py
gianna/assistants/audio/recorders/m4a.py
gianna/assistants/audio/recorders/mp3.py
gianna/assistants/audio/recorders/ogg.py
gianna/assistants/audio/recorders/wave.py
gianna/assistants/audio/stt/__init__.py
gianna/assistants/audio/stt/abstract_loaders.py
gianna/assistants/audio/stt/factory_method.py
gianna/assistants/audio/stt/m4a.py
gianna/assistants/audio/stt/mp3.py
gianna/assistants/audio/stt/whisper.py
gianna/assistants/audio/stt/whisper_local.py
gianna/assistants/audio/stt/parsers/__init__.py
gianna/assistants/audio/stt/parsers/whisper_local/__init__.py
gianna/assistants/audio/stt/parsers/whisper_local/parsers.py
gianna/assistants/audio/stt/parsers/whisper_local/whisper_cmd.py
gianna/assistants/audio/tts/__init__.py
gianna/assistants/audio/tts/abstracts.py
gianna/assistants/audio/tts/elevenlabs.py
gianna/assistants/audio/tts/factories.py
gianna/assistants/audio/tts/factory_method.py
gianna/assistants/audio/tts/google_api.py
gianna/assistants/audio/tts/whisper.py
gianna/assistants/commands/__init__.py
gianna/assistants/commands/abstracts.py
gianna/assistants/commands/bases.py
gianna/assistants/commands/factory_method.py
gianna/assistants/commands/register.py
gianna/assistants/commands/shell.py
gianna-0.1.4.dist-info/LICENSE
gianna-0.1.4.dist-info/METADATA
gianna-0.1.4.dist-info/WHEEL
gianna-0.1.4.dist-info/top_level.txt
gianna-0.1.4.dist-info/RECORD
