Metadata-Version: 2.1
Name: gianna
Version: 0.1.4
Summary: Generative Intelligent Artificial Neural Network Assistant
Home-page: https://github.com/marvinbraga/gianna
Author: Marcus Braga
Author-email: mvbraga@gmail.com
License: Apache License 2.0
Keywords: voice-assistant AI CrewAI Langchain OpenAI Google NVIDIA Groq Ollama
Classifier: Programming Language :: Python :: 3
Classifier: Operating System :: OS Independent
Requires-Python: >=3.11,<=3.13
License-File: LICENSE
Requires-Dist: crewai >=0.28.8
Requires-Dist: crewai-tools >=0.1.7
Requires-Dist: langchain-google-genai >=1.0.2
Requires-Dist: langchain-nvidia-ai-endpoints >=0.0.6
Requires-Dist: langchain-groq >=0.1.2
Requires-Dist: pydub >=0.25.1
Requires-Dist: pyaudio >=0.2.14
Requires-Dist: gtts >=2.5.1
Requires-Dist: openai >=1.20.0
Requires-Dist: elevenlabs >=1.0.5
Requires-Dist: pyperclip >=1.8.2
Requires-Dist: loguru >=0.7.2
